{
  "entries": {
    "brew": {
      "sqlite": {
        "version": "3.32.3",
        "bottle": {
          "cellar": ":any",
          "prefix": "/usr/local",
          "files": {
            "catalina": {
              "url": "https://homebrew.bintray.com/bottles/sqlite-3.32.3.catalina.bottle.tar.gz",
              "sha256": "98f798c4a62c9db46cc6ac82c499a0a1b8016dfebdfaa54eb4bf5c95a90117b0"
            },
            "mojave": {
              "url": "https://homebrew.bintray.com/bottles/sqlite-3.32.3.mojave.bottle.tar.gz",
              "sha256": "b89dc46dace451b2adc7f7e1c7456788cb3b74b3250d6183b0b7396bc00d7ccb"
            },
            "high_sierra": {
              "url": "https://homebrew.bintray.com/bottles/sqlite-3.32.3.high_sierra.bottle.tar.gz",
              "sha256": "9e117bfa603411bd552142da715ed9db8bd951e524e3d4ee7987cfeffcdf7b9d"
            }
          }
        }
      },
      "readline": {
        "version": "8.0.4",
        "bottle": {
          "cellar": ":any",
          "prefix": "/usr/local",
          "files": {
            "catalina": {
              "url": "https://homebrew.bintray.com/bottles/readline-8.0.4.catalina.bottle.tar.gz",
              "sha256": "6ae1c8e7c783f32bd22c6085caa4d838fed7fb386da7e40ca47b87ec9b1237d6"
            },
            "mojave": {
              "url": "https://homebrew.bintray.com/bottles/readline-8.0.4.mojave.bottle.tar.gz",
              "sha256": "29f7102a730ab39c8312cad1e7e439f6da2a67c452ce2b3380581eb185a5d8e8"
            },
            "high_sierra": {
              "url": "https://homebrew.bintray.com/bottles/readline-8.0.4.high_sierra.bottle.tar.gz",
              "sha256": "896a3d50ce8962ba56e853bdd590fadeabc00ab36475d143d6c2bea5cc15bb28"
            }
          }
        }
      },
      "rlwrap": {
        "version": "0.43_1",
        "bottle": {
          "cellar": "/usr/local/Cellar",
          "prefix": "/usr/local",
          "files": {
            "catalina": {
              "url": "https://homebrew.bintray.com/bottles/rlwrap-0.43_1.catalina.bottle.tar.gz",
              "sha256": "d4a2ef8e6f2c143c9156ed301d9b835b74b8e1c8bb232feb7fd8494e5262441c"
            },
            "mojave": {
              "url": "https://homebrew.bintray.com/bottles/rlwrap-0.43_1.mojave.bottle.tar.gz",
              "sha256": "1bd82e889c7f88df7b45b31201d563d7185c362c7a5d3814b5474d295de65f22"
            },
            "high_sierra": {
              "url": "https://homebrew.bintray.com/bottles/rlwrap-0.43_1.high_sierra.bottle.tar.gz",
              "sha256": "d8d5c5402f1b0041bc26c2161b2822cfd025e93674a7a5dc0046185d5870181d"
            },
            "sierra": {
              "url": "https://homebrew.bintray.com/bottles/rlwrap-0.43_1.sierra.bottle.tar.gz",
              "sha256": "3dd6233bbef1327553b5bd92d070c4d7bd24f5414628c1c367c4c3ad6f1acc76"
            }
          }
        }
      },
      "expect": {
        "version": "5.45.4",
        "bottle": {
          "cellar": "/usr/local/Cellar",
          "prefix": "/usr/local",
          "files": {
            "catalina": {
              "url": "https://homebrew.bintray.com/bottles/expect-5.45.4.catalina.bottle.1.tar.gz",
              "sha256": "f7c101cd2eec5832de103e3535e876de15b53a96a301d4848990ab8af992f3a6"
            },
            "mojave": {
              "url": "https://homebrew.bintray.com/bottles/expect-5.45.4.mojave.bottle.1.tar.gz",
              "sha256": "668b4fb12eed5bbf783e8b4ec52dad24b88f38af5577ba1e45ed9947e50e50ef"
            },
            "high_sierra": {
              "url": "https://homebrew.bintray.com/bottles/expect-5.45.4.high_sierra.bottle.1.tar.gz",
              "sha256": "a0c6ffe797dc0bbe512b628819acee67a7a9b00573b6433fe0672285d41a9df1"
            },
            "sierra": {
              "url": "https://homebrew.bintray.com/bottles/expect-5.45.4.sierra.bottle.1.tar.gz",
              "sha256": "fc9ad781caaf8d45f47a87d4303645faa2e600852c73fd5432f0be2e588e95f2"
            },
            "el_capitan": {
              "url": "https://homebrew.bintray.com/bottles/expect-5.45.4.el_capitan.bottle.1.tar.gz",
              "sha256": "4fcb163b1b1e7e209b632c43ba03106ca1c4e4d6a745260b813d28a803581e58"
            }
          }
        }
      },
      "angle-grinder": {
        "version": "0.13.0_1",
        "bottle": {
          "cellar": ":any_skip_relocation",
          "prefix": "/usr/local",
          "files": {
            "catalina": {
              "url": "https://homebrew.bintray.com/bottles/angle-grinder-0.13.0_1.catalina.bottle.tar.gz",
              "sha256": "ab4027c863beaa9da3593844c89465ec95ba88d829ef76b4eb0b6c648d01af9a"
            },
            "mojave": {
              "url": "https://homebrew.bintray.com/bottles/angle-grinder-0.13.0_1.mojave.bottle.tar.gz",
              "sha256": "5d1c7560b7a8e0437d7534253ad360d9d5d0560d2d8f2e092461691faf0e30fa"
            },
            "high_sierra": {
              "url": "https://homebrew.bintray.com/bottles/angle-grinder-0.13.0_1.high_sierra.bottle.tar.gz",
              "sha256": "4aedebd2abddc24893f849fd86830efc1247739782fdf239ea04ef6cf25fcd2b"
            }
          }
        }
      },
      "jq": {
        "version": "1.6",
        "bottle": {
          "cellar": ":any",
          "prefix": "/usr/local",
          "files": {
            "catalina": {
              "url": "https://homebrew.bintray.com/bottles/jq-1.6.catalina.bottle.1.tar.gz",
              "sha256": "820a3c85fcbb63088b160c7edf125d7e55fc2c5c1d51569304499c9cc4b89ce8"
            },
            "mojave": {
              "url": "https://homebrew.bintray.com/bottles/jq-1.6.mojave.bottle.1.tar.gz",
              "sha256": "71f0e76c5b22e5088426c971d5e795fe67abee7af6c2c4ae0cf4c0eb98ed21ff"
            },
            "high_sierra": {
              "url": "https://homebrew.bintray.com/bottles/jq-1.6.high_sierra.bottle.1.tar.gz",
              "sha256": "dffcffa4ea13e8f0f2b45c5121e529077e135ae9a47254c32182231662ee9b72"
            },
            "sierra": {
              "url": "https://homebrew.bintray.com/bottles/jq-1.6.sierra.bottle.1.tar.gz",
              "sha256": "bb4d19dc026c2d72c53eed78eaa0ab982e9fcad2cd2acc6d13e7a12ff658e877"
            }
          }
        }
      },
      "fd": {
        "version": "8.1.1",
        "bottle": {
          "cellar": ":any_skip_relocation",
          "prefix": "/usr/local",
          "files": {
            "catalina": {
              "url": "https://homebrew.bintray.com/bottles/fd-8.1.1.catalina.bottle.tar.gz",
              "sha256": "4625e56da438b94dfe331a2fe1df759b140931241af097df91f29d8ac314f2d3"
            },
            "mojave": {
              "url": "https://homebrew.bintray.com/bottles/fd-8.1.1.mojave.bottle.tar.gz",
              "sha256": "d002e8d8de192b6fad189ff7830d4fe9fc7d4ca9e81aa5ac66bb5200c590703a"
            },
            "high_sierra": {
              "url": "https://homebrew.bintray.com/bottles/fd-8.1.1.high_sierra.bottle.tar.gz",
              "sha256": "c269bbc76090614e7262c81e1b21d784050a71a51a5921686845f0d3c0855400"
            }
          }
        }
      },
      "grep": {
        "version": "3.4",
        "bottle": {
          "cellar": ":any",
          "prefix": "/usr/local",
          "files": {
            "catalina": {
              "url": "https://homebrew.bintray.com/bottles/grep-3.4.catalina.bottle.tar.gz",
              "sha256": "52fb744dfc1f2766b41d90bc4126bc6101663d12c3e31446719ef723b7883266"
            },
            "mojave": {
              "url": "https://homebrew.bintray.com/bottles/grep-3.4.mojave.bottle.tar.gz",
              "sha256": "cbce0c10ed3edc352347287ec36a8a199bb7649892943a6948e4dbe4127e83ac"
            },
            "high_sierra": {
              "url": "https://homebrew.bintray.com/bottles/grep-3.4.high_sierra.bottle.tar.gz",
              "sha256": "bcc9802f916e1db94b2879ff66b058d42142b391bfbc2002fd1fb13fd9e4c8ca"
            }
          }
        }
      },
      "ripgrep": {
        "version": "12.1.1",
        "bottle": {
          "cellar": ":any",
          "prefix": "/usr/local",
          "files": {
            "catalina": {
              "url": "https://homebrew.bintray.com/bottles/ripgrep-12.1.1.catalina.bottle.tar.gz",
              "sha256": "60460d422253113af3ed60332104f309638942821c655332211a6bc2213c472c"
            },
            "mojave": {
              "url": "https://homebrew.bintray.com/bottles/ripgrep-12.1.1.mojave.bottle.tar.gz",
              "sha256": "de4b18789f5d9bc4aaa4d906501200ae4ece7a1971dd1b86e2b2d0a2c8e0d764"
            },
            "high_sierra": {
              "url": "https://homebrew.bintray.com/bottles/ripgrep-12.1.1.high_sierra.bottle.tar.gz",
              "sha256": "cfea5335bf4eccfb7cd1d93bec234d96bd49dce8d593ea966687f777909ba291"
            }
          }
        }
      },
      "the_silver_searcher": {
        "version": "2.2.0",
        "bottle": {
          "cellar": ":any",
          "prefix": "/usr/local",
          "files": {
            "catalina": {
              "url": "https://homebrew.bintray.com/bottles/the_silver_searcher-2.2.0.catalina.bottle.tar.gz",
              "sha256": "6fd80fdd0896dae09c01d3c9785ddd658bb5f2f229e7d011d3fbdde887bc35d0"
            },
            "mojave": {
              "url": "https://homebrew.bintray.com/bottles/the_silver_searcher-2.2.0.mojave.bottle.tar.gz",
              "sha256": "e57f89664f48c131dfb462dc4be2f5265867d827f82efb1c3841ba71d9156ed0"
            },
            "high_sierra": {
              "url": "https://homebrew.bintray.com/bottles/the_silver_searcher-2.2.0.high_sierra.bottle.tar.gz",
              "sha256": "0bf5394d8ab5f61b8fbb593249f556f13b358d16eb0d3c97215be3da0476e94b"
            },
            "sierra": {
              "url": "https://homebrew.bintray.com/bottles/the_silver_searcher-2.2.0.sierra.bottle.tar.gz",
              "sha256": "2365e24e5d0b1bef64b35c6a8f9e4f61d1f38eafe38c06d6e0acefc6a9a955db"
            },
            "el_capitan": {
              "url": "https://homebrew.bintray.com/bottles/the_silver_searcher-2.2.0.el_capitan.bottle.tar.gz",
              "sha256": "1f35dcee133d638a16462db711560b624020e9dd8f732ac5a6f13a09b694421a"
            }
          }
        }
      },
      "neovim": {
        "version": "0.4.3",
        "bottle": {
          "cellar": "/usr/local/Cellar",
          "prefix": "/usr/local",
          "files": {
            "catalina": {
              "url": "https://homebrew.bintray.com/bottles/neovim-0.4.3.catalina.bottle.tar.gz",
              "sha256": "389ab254794ea04df8a106bf281c227c4fdee27c609d52951f32b9a0239031d6"
            },
            "mojave": {
              "url": "https://homebrew.bintray.com/bottles/neovim-0.4.3.mojave.bottle.tar.gz",
              "sha256": "fb6cc38c45be4650a4a750a314cec27f6f7643dc7c22a1f5abae347e1b39b388"
            },
            "high_sierra": {
              "url": "https://homebrew.bintray.com/bottles/neovim-0.4.3.high_sierra.bottle.tar.gz",
              "sha256": "b2f7450e005f4eb22bfaf650fe7741fa8629393a947b4dd48c9f91e7fc258113"
            }
          }
        }
      },
      "tmux": {
        "version": "3.1b",
        "bottle": {
          "cellar": ":any",
          "prefix": "/usr/local",
          "files": {
            "catalina": {
              "url": "https://homebrew.bintray.com/bottles/tmux-3.1b.catalina.bottle.1.tar.gz",
              "sha256": "785c1b2e2518478621eb5ac894b3f0ed06d8fdc4d223dd476451ab26974e3803"
            },
            "mojave": {
              "url": "https://homebrew.bintray.com/bottles/tmux-3.1b.mojave.bottle.1.tar.gz",
              "sha256": "a8fb2df02c2e094404b6c56e2b9d15a35abd012913771ad311e08cc3572f0e4b"
            },
            "high_sierra": {
              "url": "https://homebrew.bintray.com/bottles/tmux-3.1b.high_sierra.bottle.1.tar.gz",
              "sha256": "5d43e03fc71740ec38c98b309adb2b6d198a20fcb14f76bc163232fda61fac23"
            }
          }
        }
      },
      "screen": {
        "version": "4.8.0",
        "bottle": {
          "cellar": "/usr/local/Cellar",
          "prefix": "/usr/local",
          "files": {
            "catalina": {
              "url": "https://homebrew.bintray.com/bottles/screen-4.8.0.catalina.bottle.tar.gz",
              "sha256": "f3787a0e1c889106ab14d89c4f1bed001716ce1eb79e44e56b20e71b7448e172"
            },
            "mojave": {
              "url": "https://homebrew.bintray.com/bottles/screen-4.8.0.mojave.bottle.tar.gz",
              "sha256": "30dfe7b1bc6c74d64be57224852e50ebd5d4c6d4939872eaceac5f06d9935208"
            },
            "high_sierra": {
              "url": "https://homebrew.bintray.com/bottles/screen-4.8.0.high_sierra.bottle.tar.gz",
              "sha256": "1e63b4fd4ae798111980a7d9ed47c3fcb867cbad2c4253164b55722efc65d53e"
            }
          }
        }
      },
      "zsh": {
        "version": "5.8",
        "bottle": {
          "cellar": "/usr/local/Cellar",
          "prefix": "/usr/local",
          "files": {
            "catalina": {
              "url": "https://homebrew.bintray.com/bottles/zsh-5.8.catalina.bottle.tar.gz",
              "sha256": "209d04a4d62f6162f1b6cf824d2c50b00b52cb812c04c1967e5b376573b5aef0"
            },
            "mojave": {
              "url": "https://homebrew.bintray.com/bottles/zsh-5.8.mojave.bottle.tar.gz",
              "sha256": "c5c35657637c97132efbaa0fd8e2add568aaa62adfe66e7d19f961f8e9506da9"
            },
            "high_sierra": {
              "url": "https://homebrew.bintray.com/bottles/zsh-5.8.high_sierra.bottle.tar.gz",
              "sha256": "029b8c6922f01bfd832dd0f4f940f99328d2495714c37c1dc7ef326d6fb1459e"
            }
          }
        }
      },
      "bash": {
        "version": "5.0.17",
        "bottle": {
          "cellar": "/usr/local/Cellar",
          "prefix": "/usr/local",
          "files": {
            "catalina": {
              "url": "https://homebrew.bintray.com/bottles/bash-5.0.17.catalina.bottle.tar.gz",
              "sha256": "ce9312721ce3700e3b95d3e2f663ee51c16423cea9e54a867ad17a1f9676aa68"
            },
            "mojave": {
              "url": "https://homebrew.bintray.com/bottles/bash-5.0.17.mojave.bottle.tar.gz",
              "sha256": "0a002b85e82af9ada464528e5e34180897cde3f26f77b04944cc45d4f6bff9d8"
            },
            "high_sierra": {
              "url": "https://homebrew.bintray.com/bottles/bash-5.0.17.high_sierra.bottle.tar.gz",
              "sha256": "7711a176d742d4df6c92930da1b56e45b44075ab6839f5e7ea8eefa4227701d4"
            }
          }
        }
      },
      "fish": {
        "version": "3.1.2",
        "bottle": {
          "cellar": ":any_skip_relocation",
          "prefix": "/usr/local",
          "files": {
            "catalina": {
              "url": "https://homebrew.bintray.com/bottles/fish-3.1.2.catalina.bottle.tar.gz",
              "sha256": "b158b7f8640feb7c622ff3ca92b1bd88565f274f3e761499f5926bb124eeff7d"
            },
            "mojave": {
              "url": "https://homebrew.bintray.com/bottles/fish-3.1.2.mojave.bottle.tar.gz",
              "sha256": "6797636eaba364d0cbbc0459103a8767598e985f01846cca6cb57c986dfee7b8"
            },
            "high_sierra": {
              "url": "https://homebrew.bintray.com/bottles/fish-3.1.2.high_sierra.bottle.tar.gz",
              "sha256": "2609577a0d9f6b661331adccf5d1d8e010662ffe128869757e0af9a6760e26fb"
            }
          }
        }
      },
      "bat": {
        "version": "0.15.4",
        "bottle": {
          "cellar": ":any_skip_relocation",
          "prefix": "/usr/local",
          "files": {
            "catalina": {
              "url": "https://homebrew.bintray.com/bottles/bat-0.15.4.catalina.bottle.tar.gz",
              "sha256": "ae2c26d25a0dac35bd839a091f89201b5d9eee32ef613325426c7e8b8812d1a9"
            },
            "mojave": {
              "url": "https://homebrew.bintray.com/bottles/bat-0.15.4.mojave.bottle.tar.gz",
              "sha256": "40dea8577c06a08d3e3bd20a949245ff02ea85153d25f72a65cee03c1b1e1cf9"
            },
            "high_sierra": {
              "url": "https://homebrew.bintray.com/bottles/bat-0.15.4.high_sierra.bottle.tar.gz",
              "sha256": "59bed16f8a4741a9d92f62cb7c9965d1abe40dc5dd2323bc4f37e71330b1abf2"
            }
          }
        }
      },
      "exa": {
        "version": "0.9.0",
        "bottle": {
          "cellar": ":any_skip_relocation",
          "prefix": "/usr/local",
          "files": {
            "catalina": {
              "url": "https://homebrew.bintray.com/bottles/exa-0.9.0.catalina.bottle.tar.gz",
              "sha256": "cc484e7deb12cdae4ede810258be0ca069d7db395897e9d3fbadd501fb075743"
            },
            "mojave": {
              "url": "https://homebrew.bintray.com/bottles/exa-0.9.0.mojave.bottle.tar.gz",
              "sha256": "bc80009ad845d914c08e6de1c39c97e0f4f180ef4f077b3ef1957cab519d6743"
            },
            "high_sierra": {
              "url": "https://homebrew.bintray.com/bottles/exa-0.9.0.high_sierra.bottle.tar.gz",
              "sha256": "7382b758899c756f94c4c99440f71075945d333e302e53139e423fb1798c852e"
            },
            "sierra": {
              "url": "https://homebrew.bintray.com/bottles/exa-0.9.0.sierra.bottle.tar.gz",
              "sha256": "9499359da5f5fffbd8b22c8cb8e78f0fdf99594c4d2b06e7ba58eb21afbcb582"
            }
          }
        }
      },
      "fzf": {
        "version": "0.21.1",
        "bottle": {
          "cellar": ":any_skip_relocation",
          "prefix": "/usr/local",
          "files": {
            "catalina": {
              "url": "https://homebrew.bintray.com/bottles/fzf-0.21.1.catalina.bottle.tar.gz",
              "sha256": "733f79496c3246979ca05eeb5677a5fd9e8ec532e69e8b2012102cacddba8ae6"
            },
            "mojave": {
              "url": "https://homebrew.bintray.com/bottles/fzf-0.21.1.mojave.bottle.tar.gz",
              "sha256": "3c03bb9715be153a0f776d06cf4acd436ad4faa4266f7bd875a0d37594291516"
            },
            "high_sierra": {
              "url": "https://homebrew.bintray.com/bottles/fzf-0.21.1.high_sierra.bottle.tar.gz",
              "sha256": "d15a616156eb92071f1cfc50f10366532af92ca1635d309162141ad67f785865"
            }
          }
        }
      },
      "tokei": {
        "version": "12.0.4",
        "bottle": {
          "cellar": ":any_skip_relocation",
          "prefix": "/usr/local",
          "files": {
            "catalina": {
              "url": "https://homebrew.bintray.com/bottles/tokei-12.0.4.catalina.bottle.tar.gz",
              "sha256": "c5864a5bcefee2ab0819cd07449839ab9189d04aa8ac3302c0bab85536b6c508"
            },
            "mojave": {
              "url": "https://homebrew.bintray.com/bottles/tokei-12.0.4.mojave.bottle.tar.gz",
              "sha256": "c40027988a8081bcd64f3fb5b4905d2efbba7d55231b0084d38578c268ea924a"
            },
            "high_sierra": {
              "url": "https://homebrew.bintray.com/bottles/tokei-12.0.4.high_sierra.bottle.tar.gz",
              "sha256": "3c2cb79394bdc792fb1880842077dabfc7b038f1126e29e66d4acba5349b0253"
            }
          }
        }
      },
      "lnav": {
        "version": "0.8.5_1",
        "bottle": {
          "cellar": ":any_skip_relocation",
          "prefix": "/usr/local",
          "files": {
            "catalina": {
              "url": "https://homebrew.bintray.com/bottles/lnav-0.8.5_1.catalina.bottle.tar.gz",
              "sha256": "ada56b43c4f4301dd5c6a48502a4f801c1871b95c84aad6aeebfb0370ef4bc97"
            },
            "mojave": {
              "url": "https://homebrew.bintray.com/bottles/lnav-0.8.5_1.mojave.bottle.tar.gz",
              "sha256": "2c6e7bd10eb78c6f476739be3e106012d6decce1d8ff1ae1a51c55f3cea2c688"
            },
            "high_sierra": {
              "url": "https://homebrew.bintray.com/bottles/lnav-0.8.5_1.high_sierra.bottle.tar.gz",
              "sha256": "bc796136677ca2b4bee92decf2d517ee0a92a6ea2d476b45a350d5aff367c948"
            },
            "sierra": {
              "url": "https://homebrew.bintray.com/bottles/lnav-0.8.5_1.sierra.bottle.tar.gz",
              "sha256": "91968b3b06733d667459ca2ffb81e82b91d10e4710c22f72a739e2eed203ba1e"
            }
          }
        }
      },
      "less": {
        "version": "551",
        "bottle": {
          "cellar": ":any",
          "prefix": "/usr/local",
          "files": {
            "catalina": {
              "url": "https://homebrew.bintray.com/bottles/less-551.catalina.bottle.tar.gz",
              "sha256": "a76b3f1fb43e1e0ab566a70eca5430afa744d6d87430b55e9a5b98160834c8b9"
            },
            "mojave": {
              "url": "https://homebrew.bintray.com/bottles/less-551.mojave.bottle.tar.gz",
              "sha256": "2ee3f16d15855ab88ad87067085c0f2dd58c90c5b91ae51499ae0548a24693b2"
            },
            "high_sierra": {
              "url": "https://homebrew.bintray.com/bottles/less-551.high_sierra.bottle.tar.gz",
              "sha256": "46cd5ba33b6a1d00cfa3993712ea617bce5b6c9908b016a72413f370eda714be"
            }
          }
        }
      },
      "fpp": {
        "version": "0.9.2_1",
        "bottle": false
      },
      "aria2": {
        "version": "1.35.0",
        "bottle": {
          "cellar": ":any",
          "prefix": "/usr/local",
          "files": {
            "catalina": {
              "url": "https://homebrew.bintray.com/bottles/aria2-1.35.0.catalina.bottle.tar.gz",
              "sha256": "9cc5e04be8b0a58d1f2b60b8abfc636168edbf23e7018003c40f1dd6952aab0c"
            },
            "mojave": {
              "url": "https://homebrew.bintray.com/bottles/aria2-1.35.0.mojave.bottle.tar.gz",
              "sha256": "761836ac608eb0a59d4a6f6065860c0e809ce454692e0937d9d0d89ad47f3ce4"
            },
            "high_sierra": {
              "url": "https://homebrew.bintray.com/bottles/aria2-1.35.0.high_sierra.bottle.tar.gz",
              "sha256": "70cc7566a23c283015368f92dfeaa0d119e53cfc7c1b2276a73ff9f6167b529d"
            }
          }
        }
      },
      "wget": {
        "version": "1.20.3_2",
        "bottle": {
          "cellar": "/usr/local/Cellar",
          "prefix": "/usr/local",
          "files": {
            "catalina": {
              "url": "https://homebrew.bintray.com/bottles/wget-1.20.3_2.catalina.bottle.tar.gz",
              "sha256": "ef65c759c5097a36323fa9c77756468649e8d1980a3a4e05695c05e39568967c"
            },
            "mojave": {
              "url": "https://homebrew.bintray.com/bottles/wget-1.20.3_2.mojave.bottle.tar.gz",
              "sha256": "28f4090610946a4eb207df102d841de23ced0d06ba31cb79e040d883906dcd4f"
            },
            "high_sierra": {
              "url": "https://homebrew.bintray.com/bottles/wget-1.20.3_2.high_sierra.bottle.tar.gz",
              "sha256": "91dd0caca9bd3f38c439d5a7b6f68440c4274945615fae035ff0a369264b8a2f"
            }
          }
        }
      },
      "curl": {
        "version": "7.71.1",
        "bottle": {
          "cellar": ":any",
          "prefix": "/usr/local",
          "files": {
            "catalina": {
              "url": "https://homebrew.bintray.com/bottles/curl-7.71.1.catalina.bottle.tar.gz",
              "sha256": "36dc71f1899b803ab093e727c920b40f91b197402d9c73124c86d02feb0023c5"
            },
            "mojave": {
              "url": "https://homebrew.bintray.com/bottles/curl-7.71.1.mojave.bottle.tar.gz",
              "sha256": "99d574c0dec0a50f21ce736d77759038353f2301c7d7a64d5855d311aac4b506"
            },
            "high_sierra": {
              "url": "https://homebrew.bintray.com/bottles/curl-7.71.1.high_sierra.bottle.tar.gz",
              "sha256": "083d119978d82e86d68567b5fc48faf3d80bf66bf3f6e1c21400a2462d3c460c"
            }
          }
        }
      },
      "colordiff": {
        "version": "1.0.19",
        "bottle": {
          "cellar": ":any_skip_relocation",
          "prefix": "/usr/local",
          "files": {
            "catalina": {
              "url": "https://homebrew.bintray.com/bottles/colordiff-1.0.19.catalina.bottle.tar.gz",
              "sha256": "f0433560a0417e350a57ad24a80d277cb3cc2665046a10d8db630ef432529603"
            },
            "mojave": {
              "url": "https://homebrew.bintray.com/bottles/colordiff-1.0.19.mojave.bottle.tar.gz",
              "sha256": "f0433560a0417e350a57ad24a80d277cb3cc2665046a10d8db630ef432529603"
            },
            "high_sierra": {
              "url": "https://homebrew.bintray.com/bottles/colordiff-1.0.19.high_sierra.bottle.tar.gz",
              "sha256": "f0433560a0417e350a57ad24a80d277cb3cc2665046a10d8db630ef432529603"
            }
          }
        }
      },
      "diff-so-fancy": {
        "version": "1.3.0",
        "bottle": false
      },
      "binutils": {
        "version": "2.34",
        "bottle": {
          "cellar": "/usr/local/Cellar",
          "prefix": "/usr/local",
          "files": {
            "catalina": {
              "url": "https://homebrew.bintray.com/bottles/binutils-2.34.catalina.bottle.tar.gz",
              "sha256": "1e21593a927df65e405f9d3bdc8f86fe83b1236c5c945641a2de775c99327953"
            },
            "mojave": {
              "url": "https://homebrew.bintray.com/bottles/binutils-2.34.mojave.bottle.tar.gz",
              "sha256": "142e380448ac77bc0f7974ff9b9ddae6a90c4ef5f182cac0c2b029baa8460173"
            },
            "high_sierra": {
              "url": "https://homebrew.bintray.com/bottles/binutils-2.34.high_sierra.bottle.tar.gz",
              "sha256": "87bda0c909a5bd2043d35b073f2268cac7aed074a89d903973e4909d68dfdf46"
            }
          }
        }
      },
      "coreutils": {
        "version": "8.32",
        "bottle": {
          "cellar": "/usr/local/Cellar",
          "prefix": "/usr/local",
          "files": {
            "catalina": {
              "url": "https://homebrew.bintray.com/bottles/coreutils-8.32.catalina.bottle.tar.gz",
              "sha256": "67a4452d75a1882bd7fb977b384204edfa2758276d66290e595487922368e093"
            },
            "mojave": {
              "url": "https://homebrew.bintray.com/bottles/coreutils-8.32.mojave.bottle.tar.gz",
              "sha256": "5da6cb9dbc0a8144480dde2fb78eb0a5a1710490afc3697174f7e261ec69763f"
            },
            "high_sierra": {
              "url": "https://homebrew.bintray.com/bottles/coreutils-8.32.high_sierra.bottle.tar.gz",
              "sha256": "caa8cd8965727d0e805eccdc3e306cd0599720cdd0d5417cfcca03bead670663"
            }
          }
        }
      },
      "diffutils": {
        "version": "3.7",
        "bottle": {
          "cellar": ":any_skip_relocation",
          "prefix": "/usr/local",
          "files": {
            "catalina": {
              "url": "https://homebrew.bintray.com/bottles/diffutils-3.7.catalina.bottle.tar.gz",
              "sha256": "25a2f5fcdfcdf2efa36b97841e45455950fe322e1c642d97a36abbb2662007cf"
            },
            "mojave": {
              "url": "https://homebrew.bintray.com/bottles/diffutils-3.7.mojave.bottle.tar.gz",
              "sha256": "4ec2a5ef0ca889d6c449b31ed43c797a0656ff7a2acfd913d0f87d8f14248031"
            },
            "high_sierra": {
              "url": "https://homebrew.bintray.com/bottles/diffutils-3.7.high_sierra.bottle.tar.gz",
              "sha256": "fe012f4e981c3df3b2d1b3eb2b77009991148e3bdc08dd974d6f6071108e8937"
            },
            "sierra": {
              "url": "https://homebrew.bintray.com/bottles/diffutils-3.7.sierra.bottle.tar.gz",
              "sha256": "3a04e2e2de81458a8fc75482a97a02883a1cdf231ee340ce30d9a712d0475305"
            }
          }
        }
      },
      "findutils": {
        "version": "4.7.0",
        "bottle": {
          "cellar": ":any_skip_relocation",
          "prefix": "/usr/local",
          "files": {
            "catalina": {
              "url": "https://homebrew.bintray.com/bottles/findutils-4.7.0.catalina.bottle.tar.gz",
              "sha256": "f9ba06f4d48275e8cab659450b05e77873e909f31104df450201a83d465ed1ca"
            },
            "mojave": {
              "url": "https://homebrew.bintray.com/bottles/findutils-4.7.0.mojave.bottle.tar.gz",
              "sha256": "3c609b729a1dc859459282a856ff6c164cd8388e531dad4e58c8d4c7acb670fb"
            },
            "high_sierra": {
              "url": "https://homebrew.bintray.com/bottles/findutils-4.7.0.high_sierra.bottle.tar.gz",
              "sha256": "996a9fe2b1829fdf7b7257bead0ef0c4315832e9ba21b149779abeb59dcbde30"
            },
            "sierra": {
              "url": "https://homebrew.bintray.com/bottles/findutils-4.7.0.sierra.bottle.tar.gz",
              "sha256": "4b66ce398f2d5f5c65bf0b05fcc55334398e75cb965a17d781d7c3a15a4bba61"
            }
          }
        }
      },
      "git": {
        "version": "2.27.0",
        "bottle": {
          "cellar": "/usr/local/Cellar",
          "prefix": "/usr/local",
          "files": {
            "catalina": {
              "url": "https://homebrew.bintray.com/bottles/git-2.27.0.catalina.bottle.1.tar.gz",
              "sha256": "731a77dd23d63ca8a0a5ba5c990218e37f1c8d9313fa1f9e58771cf5abd97bef"
            },
            "mojave": {
              "url": "https://homebrew.bintray.com/bottles/git-2.27.0.mojave.bottle.1.tar.gz",
              "sha256": "a752212149e96e67fd8c42e1d68d7612de94bc67f06ffdc13ed7236aa33debf4"
            },
            "high_sierra": {
              "url": "https://homebrew.bintray.com/bottles/git-2.27.0.high_sierra.bottle.1.tar.gz",
              "sha256": "c9b1c7d3686fac0f7006b13b1afd46e38f2d6c73dd72049d9e8fc49b1bb34599"
            }
          }
        }
      },
      "git-extras": {
        "version": "6.0.0",
        "bottle": {
          "cellar": ":any_skip_relocation",
          "prefix": "/usr/local",
          "files": {
            "catalina": {
              "url": "https://homebrew.bintray.com/bottles/git-extras-6.0.0.catalina.bottle.1.tar.gz",
              "sha256": "6bec6d92d79cabaac6e99d15c8bf1542cf97dcb190b7e77ad4eaa8e381cff055"
            },
            "mojave": {
              "url": "https://homebrew.bintray.com/bottles/git-extras-6.0.0.mojave.bottle.1.tar.gz",
              "sha256": "6bec6d92d79cabaac6e99d15c8bf1542cf97dcb190b7e77ad4eaa8e381cff055"
            },
            "high_sierra": {
              "url": "https://homebrew.bintray.com/bottles/git-extras-6.0.0.high_sierra.bottle.1.tar.gz",
              "sha256": "6bec6d92d79cabaac6e99d15c8bf1542cf97dcb190b7e77ad4eaa8e381cff055"
            }
          }
        }
      },
      "git-flow": {
        "version": "0.4.1",
        "bottle": {
          "cellar": ":any_skip_relocation",
          "prefix": "/usr/local",
          "files": {
            "catalina": {
              "url": "https://homebrew.bintray.com/bottles/git-flow-0.4.1.catalina.bottle.tar.gz",
              "sha256": "8ea12cd7e2666fb6fdfaffaeb3a0437037a40cde559a835fc9de038f36a424dc"
            },
            "mojave": {
              "url": "https://homebrew.bintray.com/bottles/git-flow-0.4.1.mojave.bottle.tar.gz",
              "sha256": "ab455769b6b8122e1d345f56d799fe43445bbbeba6265892715167388c737af9"
            },
            "high_sierra": {
              "url": "https://homebrew.bintray.com/bottles/git-flow-0.4.1.high_sierra.bottle.tar.gz",
              "sha256": "ce4b64f4d13f4a5a8e05c9087627b42cd328c8accc8349c4ca256238d1d3fecc"
            },
            "sierra": {
              "url": "https://homebrew.bintray.com/bottles/git-flow-0.4.1.sierra.bottle.tar.gz",
              "sha256": "acb9a2690fa86925600fa6e67e38731ef05f7f5d6ccfceb9c5175286c1081fe0"
            },
            "el_capitan": {
              "url": "https://homebrew.bintray.com/bottles/git-flow-0.4.1.el_capitan.bottle.tar.gz",
              "sha256": "56826b30d91ffb54829f4792f88c673b1c3e748aa662bef5806e4a6f5d0ee015"
            },
            "yosemite": {
              "url": "https://homebrew.bintray.com/bottles/git-flow-0.4.1.yosemite.bottle.tar.gz",
              "sha256": "a5e97d4d5c082194b36c18e7b051c43b2d5b37366b2ac56c5ea9407f6315685b"
            },
            "mavericks": {
              "url": "https://homebrew.bintray.com/bottles/git-flow-0.4.1.mavericks.bottle.tar.gz",
              "sha256": "8e931605a0d12cffa282db7244e0041cc14f8a7692e184a6bc1975800be2dac0"
            }
          }
        }
      },
      "git-lfs": {
        "version": "2.11.0",
        "bottle": {
          "cellar": ":any_skip_relocation",
          "prefix": "/usr/local",
          "files": {
            "catalina": {
              "url": "https://homebrew.bintray.com/bottles/git-lfs-2.11.0.catalina.bottle.tar.gz",
              "sha256": "351d2d6cb168249b9b7b0d55628574126b9787eab1441861dfd324b952057651"
            },
            "mojave": {
              "url": "https://homebrew.bintray.com/bottles/git-lfs-2.11.0.mojave.bottle.tar.gz",
              "sha256": "adbf311076f64920e0f621640d251e6ef44ad8fc9022f287118be5644c4095d4"
            },
            "high_sierra": {
              "url": "https://homebrew.bintray.com/bottles/git-lfs-2.11.0.high_sierra.bottle.tar.gz",
              "sha256": "0c231fb0f6edab306f9b58f08fb8c075860f688d6efe4190b6377c661e36d18c"
            }
          }
        }
      },
      "tig": {
        "version": "2.5.1",
        "bottle": {
          "cellar": ":any",
          "prefix": "/usr/local",
          "files": {
            "catalina": {
              "url": "https://homebrew.bintray.com/bottles/tig-2.5.1.catalina.bottle.tar.gz",
              "sha256": "e3dd84d1883ca04013d72311c248f623a3e55fa8fa31456f5fe956ae19ccd4de"
            },
            "mojave": {
              "url": "https://homebrew.bintray.com/bottles/tig-2.5.1.mojave.bottle.tar.gz",
              "sha256": "0fbc0ae28aed58f73b1e798cbe75c8d131762c91371bd00e5a257c3a6fda7f85"
            },
            "high_sierra": {
              "url": "https://homebrew.bintray.com/bottles/tig-2.5.1.high_sierra.bottle.tar.gz",
              "sha256": "9f6983f67cbbe6d551c8ab39131ca1e91e9f3e57ffe1f1791e6c182fd017fbf8"
            }
          }
        }
      },
      "hub": {
        "version": "2.14.2",
        "bottle": {
          "cellar": ":any_skip_relocation",
          "prefix": "/usr/local",
          "files": {
            "catalina": {
              "url": "https://homebrew.bintray.com/bottles/hub-2.14.2.catalina.bottle.tar.gz",
              "sha256": "fdf05855839a9d7ec6e7bee6796e3cb5fc473500cffc002366cf98c09a805b69"
            },
            "mojave": {
              "url": "https://homebrew.bintray.com/bottles/hub-2.14.2.mojave.bottle.tar.gz",
              "sha256": "bcbae9c683d76f3395665467ba0f0c00c60c12c84022f72faba4b8981724b563"
            },
            "high_sierra": {
              "url": "https://homebrew.bintray.com/bottles/hub-2.14.2.high_sierra.bottle.tar.gz",
              "sha256": "8800cda4532784bf764ea6116a06c81d8d90bb3d36d8ecf295e64f9dd647c4ad"
            }
          }
        }
      },
      "gist": {
        "version": "5.1.0",
        "bottle": {
          "cellar": ":any_skip_relocation",
          "prefix": "/usr/local",
          "files": {
            "catalina": {
              "url": "https://homebrew.bintray.com/bottles/gist-5.1.0.catalina.bottle.tar.gz",
              "sha256": "7eb37c0514203306a3e5be9176acca230014a30e07d43d0e9ba72afcc3dc3203"
            },
            "mojave": {
              "url": "https://homebrew.bintray.com/bottles/gist-5.1.0.mojave.bottle.tar.gz",
              "sha256": "7eb37c0514203306a3e5be9176acca230014a30e07d43d0e9ba72afcc3dc3203"
            },
            "high_sierra": {
              "url": "https://homebrew.bintray.com/bottles/gist-5.1.0.high_sierra.bottle.tar.gz",
              "sha256": "7eb37c0514203306a3e5be9176acca230014a30e07d43d0e9ba72afcc3dc3203"
            }
          }
        }
      },
      "entr": {
        "version": "4.6",
        "bottle": {
          "cellar": ":any_skip_relocation",
          "prefix": "/usr/local",
          "files": {
            "catalina": {
              "url": "https://homebrew.bintray.com/bottles/entr-4.6.catalina.bottle.tar.gz",
              "sha256": "21b69b1e641551d2022f5b261fd03d43e16e54d7eb09528890d122968de12460"
            },
            "mojave": {
              "url": "https://homebrew.bintray.com/bottles/entr-4.6.mojave.bottle.tar.gz",
              "sha256": "26cae580f66328a940c9f13add3c4cf91fae6b01247144a302757aac11e53427"
            },
            "high_sierra": {
              "url": "https://homebrew.bintray.com/bottles/entr-4.6.high_sierra.bottle.tar.gz",
              "sha256": "f37ebf2d5da20610536902c4010e4cd93136bc6282f2f3c7a119e3876c79d447"
            }
          }
        }
      },
      "cheat": {
        "version": "4.0.1",
        "bottle": {
          "cellar": ":any_skip_relocation",
          "prefix": "/usr/local",
          "files": {
            "catalina": {
              "url": "https://homebrew.bintray.com/bottles/cheat-4.0.1.catalina.bottle.tar.gz",
              "sha256": "22e47b7e9dfb461e2e9f8c3dac9ead9fe261026a0f4b4ce2b89f490253ea2962"
            },
            "mojave": {
              "url": "https://homebrew.bintray.com/bottles/cheat-4.0.1.mojave.bottle.tar.gz",
              "sha256": "c46bf0a127b1fd10e45b26e4fdf88333228f9d230f71190580891acd64a2a7bd"
            },
            "high_sierra": {
              "url": "https://homebrew.bintray.com/bottles/cheat-4.0.1.high_sierra.bottle.tar.gz",
              "sha256": "78d1fc2437cda33d65afab69eadf4870afcb0ac7a0ff6fbe55ede0af982d52a7"
            }
          }
        }
      },
      "tealdeer": {
        "version": "1.3.0_1",
        "bottle": {
          "cellar": ":any_skip_relocation",
          "prefix": "/usr/local",
          "files": {
            "catalina": {
              "url": "https://homebrew.bintray.com/bottles/tealdeer-1.3.0_1.catalina.bottle.tar.gz",
              "sha256": "9db1cd67e060652967a899a4266758bf0b460b1426bea40a822f217c4edf4d80"
            },
            "mojave": {
              "url": "https://homebrew.bintray.com/bottles/tealdeer-1.3.0_1.mojave.bottle.tar.gz",
              "sha256": "379f9775e19bf959868350869913b83458b3f14b4aacdd4e5432c2a4cdcf8e9d"
            },
            "high_sierra": {
              "url": "https://homebrew.bintray.com/bottles/tealdeer-1.3.0_1.high_sierra.bottle.tar.gz",
              "sha256": "fd5d4b07815554a32fc161accc1145d1a7ef761bd20f2f94bdb94eca57563e32"
            }
          }
        }
      },
      "unrar": {
        "version": "5.9.4",
        "bottle": {
          "cellar": ":any",
          "prefix": "/usr/local",
          "files": {
            "catalina": {
              "url": "https://homebrew.bintray.com/bottles/unrar-5.9.4.catalina.bottle.tar.gz",
              "sha256": "90e0f209046471dda292a622ded80ed410e237cb7fc8e1d2653f0d57c470fc6b"
            },
            "mojave": {
              "url": "https://homebrew.bintray.com/bottles/unrar-5.9.4.mojave.bottle.tar.gz",
              "sha256": "a45568c9d67db8866971aec111e9e6d9d606549099f60240f2cf7c7096680270"
            },
            "high_sierra": {
              "url": "https://homebrew.bintray.com/bottles/unrar-5.9.4.high_sierra.bottle.tar.gz",
              "sha256": "ca9a590d0bce2de6e35ce02fdc7a6bb2d32265a945949e278fb7ae4c8d3c2dca"
            }
          }
        }
      },
      "unzip": {
        "version": "6.0_6",
        "bottle": {
          "cellar": ":any_skip_relocation",
          "prefix": "/usr/local",
          "files": {
            "catalina": {
              "url": "https://homebrew.bintray.com/bottles/unzip-6.0_6.catalina.bottle.tar.gz",
              "sha256": "178cea56554b0e6b74856203340554c7615c6ed2e122059c78370e35c896f0ce"
            },
            "mojave": {
              "url": "https://homebrew.bintray.com/bottles/unzip-6.0_6.mojave.bottle.tar.gz",
              "sha256": "f0b95f2d5c664f45686f3aa318384906014ed28939da28020d12138f025aaeb6"
            },
            "high_sierra": {
              "url": "https://homebrew.bintray.com/bottles/unzip-6.0_6.high_sierra.bottle.tar.gz",
              "sha256": "6dd7d0862f5a8b954dd94b3c91378209e0086eec7c5be367af0d8c330bc099da"
            },
            "sierra": {
              "url": "https://homebrew.bintray.com/bottles/unzip-6.0_6.sierra.bottle.tar.gz",
              "sha256": "f4d59c04a44f93a30a23ec403784c73f9c06db9b72f3277679f66b1870a94331"
            }
          }
        }
      },
      "cliclick": {
        "version": "4.0.1",
        "bottle": {
          "cellar": ":any_skip_relocation",
          "prefix": "/usr/local",
          "files": {
            "catalina": {
              "url": "https://homebrew.bintray.com/bottles/cliclick-4.0.1.catalina.bottle.tar.gz",
              "sha256": "9ffcef6839fb396f022e415925f0e5f2cd1434d0eb723694d950d84fbaa3fcda"
            },
            "mojave": {
              "url": "https://homebrew.bintray.com/bottles/cliclick-4.0.1.mojave.bottle.tar.gz",
              "sha256": "bc373ee9ec978d416491fd82b3c25d02755b004b0abc1f5a73ff0b39e57b6b33"
            },
            "high_sierra": {
              "url": "https://homebrew.bintray.com/bottles/cliclick-4.0.1.high_sierra.bottle.tar.gz",
              "sha256": "c371cb5b700e4a5f6495545b5f83e5414fc0e0cb98be05231a7abdf6c6607ff4"
            },
            "sierra": {
              "url": "https://homebrew.bintray.com/bottles/cliclick-4.0.1.sierra.bottle.tar.gz",
              "sha256": "bb47d1d8f4c81f31dc9372b5c06d3f74ecb25026805936f62e08744d1b888ecb"
            },
            "el_capitan": {
              "url": "https://homebrew.bintray.com/bottles/cliclick-4.0.1.el_capitan.bottle.tar.gz",
              "sha256": "e8eca6037032ad2b68b9e8c4faa40adb770b10f868448e47852571f1829aa462"
            }
          }
        }
      },
      "htop": {
        "version": "2.2.0_1",
        "bottle": {
          "cellar": ":any",
          "prefix": "/usr/local",
          "files": {
            "catalina": {
              "url": "https://homebrew.bintray.com/bottles/htop-2.2.0_1.catalina.bottle.tar.gz",
              "sha256": "c06ff60960f64f5c8395f53d7419cbcce2a22ee87f0cb0138352c8a88111d21c"
            },
            "mojave": {
              "url": "https://homebrew.bintray.com/bottles/htop-2.2.0_1.mojave.bottle.tar.gz",
              "sha256": "77aa302765353b4085dcad52356d3264183e06310dda8d5bac64642299ea2902"
            },
            "high_sierra": {
              "url": "https://homebrew.bintray.com/bottles/htop-2.2.0_1.high_sierra.bottle.tar.gz",
              "sha256": "0ebfb655b91566ba31f8effc94d642a43305ff95bdc9b30b46fadc132e2ced0c"
            },
            "sierra": {
              "url": "https://homebrew.bintray.com/bottles/htop-2.2.0_1.sierra.bottle.tar.gz",
              "sha256": "ed93b86f011de155c5d261b8c9cc9cb81fd0017667bf3ebe26ee090716bcd650"
            }
          }
        }
      },
      "editorconfig": {
        "version": "0.12.3",
        "bottle": {
          "cellar": ":any",
          "prefix": "/usr/local",
          "files": {
            "catalina": {
              "url": "https://homebrew.bintray.com/bottles/editorconfig-0.12.3.catalina.bottle.tar.gz",
              "sha256": "a1315cb812fd1f626d7924543b80388f88e8cb13ee79e9f305d475bf5787217e"
            },
            "mojave": {
              "url": "https://homebrew.bintray.com/bottles/editorconfig-0.12.3.mojave.bottle.tar.gz",
              "sha256": "da824a4d67b8c1c1627d90e222b5f2441caf9cd7eca50de40380d3e7839db047"
            },
            "high_sierra": {
              "url": "https://homebrew.bintray.com/bottles/editorconfig-0.12.3.high_sierra.bottle.tar.gz",
              "sha256": "26eceb21fd8d34c04799f70ba22ca0da11456c1e3fa30b0b90e592038b840d01"
            },
            "sierra": {
              "url": "https://homebrew.bintray.com/bottles/editorconfig-0.12.3.sierra.bottle.tar.gz",
              "sha256": "a4655cde0acc92e11b02263337d384770bf0b592d828d44b8bef8be961572ad8"
            }
          }
        }
      },
      "emojify": {
        "version": "1.0.2",
        "bottle": false
      },
      "neofetch": {
        "version": "7.0.0",
        "bottle": {
          "cellar": ":any_skip_relocation",
          "prefix": "/usr/local",
          "files": {
            "catalina": {
              "url": "https://homebrew.bintray.com/bottles/neofetch-7.0.0.catalina.bottle.tar.gz",
              "sha256": "bfb4c9f42eee7659b0028a7d4de28524d5a6eb8f1199f83789fa0242b37c456e"
            },
            "mojave": {
              "url": "https://homebrew.bintray.com/bottles/neofetch-7.0.0.mojave.bottle.tar.gz",
              "sha256": "bfb4c9f42eee7659b0028a7d4de28524d5a6eb8f1199f83789fa0242b37c456e"
            },
            "high_sierra": {
              "url": "https://homebrew.bintray.com/bottles/neofetch-7.0.0.high_sierra.bottle.tar.gz",
              "sha256": "bfb4c9f42eee7659b0028a7d4de28524d5a6eb8f1199f83789fa0242b37c456e"
            }
          }
        }
      },
      "openssh": {
        "version": "8.3p1",
        "bottle": {
          "cellar": "/usr/local/Cellar",
          "prefix": "/usr/local",
          "files": {
            "catalina": {
              "url": "https://homebrew.bintray.com/bottles/openssh-8.3p1.catalina.bottle.tar.gz",
              "sha256": "3f5a9e5b5bbf82235fb47f893b71f514b10adc344c7d3c0f57b3837cfa50458f"
            },
            "mojave": {
              "url": "https://homebrew.bintray.com/bottles/openssh-8.3p1.mojave.bottle.tar.gz",
              "sha256": "d7b58684502abed77b364c5742ea4a1682e29e2df08d86a1ff6f249409e4b085"
            },
            "high_sierra": {
              "url": "https://homebrew.bintray.com/bottles/openssh-8.3p1.high_sierra.bottle.tar.gz",
              "sha256": "a096eab677ff45aa7e4e1b7da4f2a0f7ebf34ff579d6bc679858cda8d482b6c8"
            }
          }
        }
      }
    }
  },
  "system": {
    "macos": {
      "catalina": {
        "HOMEBREW_VERSION": "2.4.4",
        "HOMEBREW_PREFIX": "/usr/local",
        "Homebrew/homebrew-core": "d8ed91b79b2a6ac0560c0ad32ecfafb9f0414f1f",
        "CLT": "11.5.0.0.1.1588476445",
        "Xcode": "11.5",
        "macOS": "10.15.5"
      }
    }
  }
}
